e2e/_typing.py
e2e/cli.py
e2e/_cli/demo.py
e2e/_cli/init.py
e2e/_cli/new.py
e2e/_cli/template.py
e2e/_templates/e2e_ext/_typing.py.template
e2e/_templates/new/screen.py.template
e2e/_templates/new/simulation.py.template
e2e/core/__init__.py
e2e/core/config.py
e2e/core/env.py
e2e/core/logger.py
e2e/core/screen.py
e2e/core/simulation.py
e2e/core/tester.py
e2e/core/appium/config.py
e2e/core/mixin/__init__.py
e2e/core/mixin/ui/__init__.py
e2e/core/mixin/ui/base.py
e2e/core/mixin/ui/wd.py
e2e/core/ui/__init__.py
e2e/core/ui/base.py
e2e/core/ui/button.py
e2e/core/ui/textfield.py
e2e/core/utils/__init__.py
e2e/core/utils/app.py
e2e/core/utils/caps.py
e2e/core/utils/failable.py
e2e/core/utils/meta.py
e2e/core/utils/module.py
e2e/core/utils/wd.py
e2e/mixin/dynamic.py
e2e/pytest_plugins/__init__.py
e2e/pytest_plugins/appium_service.py
e2e/pytest_plugins/base.py
e2e/pytest_plugins/core.py
e2e/pytest_plugins/diagnostics.py
e2e/pytest_plugins/log.py
e2e/pytest_plugins/parallel.py
e2e/pytest_plugins/report.py
e2e/pytest_plugins/simulator.py
e2e/pytest_plugins/tester.py
e2e/pytest_plugins/wd.py
e2e/screens/__init__.py
e2e/simulations/__init__.py
e2e/simulations/location_update.py
e2e/simulations/push_notification.py
e2e_mobile-0.1.4.dist-info/LICENSE
e2e_mobile-0.1.4.dist-info/METADATA
e2e_mobile-0.1.4.dist-info/WHEEL
e2e_mobile-0.1.4.dist-info/entry_points.txt
e2e_mobile-0.1.4.dist-info/top_level.txt
e2e_mobile-0.1.4.dist-info/RECORD
