Metadata-Version: 2.1
Name: e2e-mobile
Version: 0.1.4
Summary: E2E Testing package for mobile apps
Author-email: Thuyen Trinh <trinhngocthuyen@gmail.com>
License: MIT
Project-URL: Homepage, https://github.com/trinhngocthuyen/e2e-mobile
Keywords: ci,cd,ci/cd,mobile,ios
Classifier: License :: OSI Approved :: MIT License
Classifier: Programming Language :: Python
Classifier: Programming Language :: Python :: 3
Classifier: Programming Language :: Python :: 3.10
Requires-Python: >=3.10
License-File: LICENSE
Requires-Dist: retry
Requires-Dist: Appium-Python-Client
Requires-Dist: pytest
Requires-Dist: click
Requires-Dist: seeeye>=0.1.1
Provides-Extra: dev
Requires-Dist: setuptools>=61.0.0; extra == "dev"
Requires-Dist: pip-tools; extra == "dev"
Requires-Dist: black; extra == "dev"
Requires-Dist: autoflake; extra == "dev"
Requires-Dist: isort; extra == "dev"
Requires-Dist: pre-commit; extra == "dev"
Requires-Dist: bumpver; extra == "dev"
Requires-Dist: twine; extra == "dev"
Requires-Dist: pytest; extra == "dev"
Requires-Dist: pytest-cov; extra == "dev"
Requires-Dist: pytest-html; extra == "dev"
Requires-Dist: sphinx-rtd-theme; extra == "dev"
